ad_searchapi-2.0.3.dist-info/licenses/LICENSE
search_api/__init__.py
search_api/client.py
search_api/exceptions.py
search_api/models.py
ad_searchapi-2.0.3.dist-info/METADATA
ad_searchapi-2.0.3.dist-info/WHEEL
ad_searchapi-2.0.3.dist-info/top_level.txt
ad_searchapi-2.0.3.dist-info/RECORD
