Metadata-Version: 2.4
Name: AD-SearchAPI
Version: 2.0.3
Summary: A comprehensive Python client library for the Search API with enhanced error handling and balance management
Home-page: https://github.com/AntiChrist-Coder/search_api_library
Author: Search API Team
Author-email: support@search-api.dev
Project-URL: Bug Reports, https://github.com/AntiChrist-Coder/search_api_library/issues
Project-URL: Source, https://github.com/AntiChrist-Coder/search_api_library
Project-URL: Documentation, https://github.com/AntiChrist-Coder/search_api_library/blob/main/README.md
Keywords: search-api,email-search,phone-search,domain-search,people-search,api-client,balance-management
Classifier: Development Status :: 5 - Production/Stable
Classifier: Intended Audience :: Developers
Classifier: License :: OSI Approved :: MIT License
Classifier: Programming Language :: Python :: 3
Classifier: Programming Language :: Python :: 3.8
Classifier: Programming Language :: Python :: 3.9
Classifier: Programming Language :: Python :: 3.10
Classifier: Programming Language :: Python :: 3.11
Classifier: Programming Language :: Python :: 3.12
Classifier: Topic :: Internet :: WWW/HTTP :: Dynamic Content
Classifier: Topic :: Software Development :: Libraries :: Python Modules
Classifier: Topic :: Communications :: Email
Classifier: Topic :: Internet :: Name Service (DNS)
Requires-Python: >=3.8
License-File: LICENSE
Requires-Dist: requests>=2.31.0
Requires-Dist: phonenumbers>=8.13.0
Requires-Dist: python-dateutil>=2.8.2
Requires-Dist: typing-extensions>=4.7.0
Requires-Dist: urllib3>=2.0.0
Provides-Extra: dev
Requires-Dist: pytest>=7.0.0; extra == "dev"
Requires-Dist: pytest-cov>=4.0.0; extra == "dev"
Requires-Dist: black>=23.0.0; extra == "dev"
Requires-Dist: flake8>=6.0.0; extra == "dev"
Requires-Dist: mypy>=1.0.0; extra == "dev"
Provides-Extra: brotli
Requires-Dist: brotli>=1.0.0; extra == "brotli"
Dynamic: author
Dynamic: author-email
Dynamic: classifier
Dynamic: description
Dynamic: description-content-type
Dynamic: home-page
Dynamic: keywords
Dynamic: license-file
Dynamic: project-url
Dynamic: provides-extra
Dynamic: requires-dist
Dynamic: requires-python
Dynamic: summary
